MANIFEST.in
README.md
setup.py
ros/__init__.py
ros/app.py
ros/cache.py
ros/celery_app.py
ros/celery_tools.py
ros/client.py
ros/config.py
ros/csvargs.py
ros/framework.py
ros/graph.py
ros/kgraph.py
ros/kgxlib.py
ros/logging.yaml
ros/out.txt
ros/redisg.py
ros/requirements.txt
ros/ros.yaml
ros/router.py
ros/stdlib.yaml
ros/tasks.py
ros/triplestore.py
ros/types.yaml
ros/util.py
ros/viz.py
ros/workflow.py
ros.egg-info/PKG-INFO
ros.egg-info/SOURCES.txt
ros.egg-info/dependency_links.txt
ros.egg-info/entry_points.txt
ros.egg-info/requires.txt
ros.egg-info/top_level.txt
ros/lib/cause.py
ros/lib/ndex.py
ros/lib/validate.py
ros/workflows/automated_validation_wf1_t2diabetes.ros
ros/workflows/bionames.ros
ros/workflows/grapherator_v1.ros
ros/workflows/grapherator_v2.ros
ros/workflows/green-cqs.ros
ros/workflows/green_mq.txt
ros/workflows/m2m_models_v1.ros
ros/workflows/workflow_one.ros
ros/workflows/workflow_one_tias.ros
ros/workflows/workflow_one_tias_v1.ros
ros/workflows/workflow_one_tias_v2.ros
ros/workflows/workflow_one_tias_v3.ros