Metadata-Version: 2.1
Name: ros
Version: 0.118
Summary: Ros Knowledge Network
Home-page: http://github.com/NCATS-Tangerine/ros.git
Author: Steve Cox
Author-email: scox@renci.org
License: UNKNOWN
Download-URL: http://github.com/NCATS-Tangerine/ros/archive/0.1.tar.gz
Keywords: knowledge,network,graph,biomedical
Platform: UNKNOWN
